AUTHORS.rst
CONTRIBUTING.rst
HISTORY.rst
LICENSE
MANIFEST.in
README.rst
setup.cfg
setup.py
broot/RootWrap.py
broot/__init__.py
broot/broot.py
broot.egg-info/PKG-INFO
broot.egg-info/SOURCES.txt
broot.egg-info/dependency_links.txt
broot.egg-info/not-zip-safe
broot.egg-info/requires.txt
broot.egg-info/top_level.txt
broot/src/RootOutput.cpp
docs/Makefile
docs/authors.rst
docs/conf.py
docs/contributing.rst
docs/history.rst
docs/index.rst
docs/installation.rst
docs/make.bat
docs/readme.rst
docs/usage.rst
tests/__init__.py
tests/test_broot.py