Metadata-Version: 1.1
Name: broot
Version: 0.1.1
Summary: Library for converting python numpy datastructures to the ROOT output format.
Home-page: https://github.com/pelssers/broot
Author: Bart Pelssers
Author-email: bartp@nikhef.nl
License: GPL2
Keywords: broot
Platform: UNKNOWN
Classifier: Development Status :: 2 - Pre-Alpha
Classifier: Intended Audience :: Developers
Classifier: Intended Audience :: Science/Research
Classifier: License :: OSI Approved :: GNU General Public License v2 (GPLv2)
Classifier: Natural Language :: English
Classifier: Programming Language :: Python :: 2
Classifier: Programming Language :: Python :: 2.6
Classifier: Programming Language :: Python :: 2.7
Classifier: Programming Language :: Python :: 3
Classifier: Programming Language :: Python :: 3.3
Classifier: Programming Language :: Python :: 3.4
Classifier: Programming Language :: C++
